heat/__init__.py
heat/cli.py
heat/py.typed
heat/array_api/__init__.py
heat/array_api/_array_object.py
heat/array_api/_constants.py
heat/array_api/_creation_functions.py
heat/array_api/_data_type_functions.py
heat/array_api/_dtypes.py
heat/array_api/_elementwise_functions.py
heat/array_api/_manipulation_functions.py
heat/array_api/_searching_functions.py
heat/array_api/_set_functions.py
heat/array_api/_sorting_functions.py
heat/array_api/_statistical_functions.py
heat/array_api/_typing.py
heat/array_api/_utility_functions.py
heat/array_api/linalg.py
heat/classification/__init__.py
heat/classification/kneighborsclassifier.py
heat/cluster/__init__.py
heat/cluster/_kcluster.py
heat/cluster/batchparallelclustering.py
heat/cluster/kmeans.py
heat/cluster/kmedians.py
heat/cluster/kmedoids.py
heat/cluster/spectral.py
heat/core/__init__.py
heat/core/_config.py
heat/core/_operations.py
heat/core/arithmetics.py
heat/core/base.py
heat/core/communication.py
heat/core/complex_math.py
heat/core/constants.py
heat/core/devices.py
heat/core/dndarray.py
heat/core/exponential.py
heat/core/factories.py
heat/core/indexing.py
heat/core/io.py
heat/core/logical.py
heat/core/manipulations.py
heat/core/memory.py
heat/core/printing.py
heat/core/random.py
heat/core/relational.py
heat/core/rounding.py
heat/core/sanitation.py
heat/core/signal.py
heat/core/statistics.py
heat/core/stride_tricks.py
heat/core/tiling.py
heat/core/trigonometrics.py
heat/core/types.py
heat/core/version.py
heat/core/vmap.py
heat/core/linalg/__init__.py
heat/core/linalg/basics.py
heat/core/linalg/eigh.py
heat/core/linalg/polar.py
heat/core/linalg/qr.py
heat/core/linalg/randomized.py
heat/core/linalg/solver.py
heat/core/linalg/svd.py
heat/core/linalg/svdtools.py
heat/datasets/__init__.py
heat/datasets/diabetes.h5
heat/datasets/iris.csv
heat/datasets/iris.h5
heat/datasets/iris.nc
heat/datasets/iris_X_test.csv
heat/datasets/iris_X_train.csv
heat/datasets/iris_labels.csv
heat/datasets/iris_y_pred_proba.csv
heat-1.7.0.dist-info/licenses/LICENSE
heat-1.7.0.dist-info/METADATA
heat-1.7.0.dist-info/WHEEL
heat-1.7.0.dist-info/entry_points.txt
heat-1.7.0.dist-info/top_level.txt
heat-1.7.0.dist-info/RECORD
