Metadata-Version: 2.4
Name: heat
Version: 1.7.0
Summary: A framework for high-performance data analytics and machine learning.
Author-email: Markus Götz <markus.goetz@kit.edu>, Charlotte Debus <charlotte.debus@kit.edu>, Daniel Coquelin <daniel.coquelin@kit.edu>, Kai Krajsek <k.krajsek@fz-juelich.de>, Claudia Comito <c.comito@fz-juelich.de>, Philipp Knechtges <philipp.knechtges@dlr.de>, Björn Hagemeier <b.hagemeier@fz-juelich.de>, Martin Siggel <martin.siggel@dlr.de>, Achim Basermann <achim.basermann@dlr.de>, Achim Streit <achim.streit@kit.de>
Maintainer-email: Claudia Comito <c.comito@fz-juelich.de>, Michael Tarnawa <m.tarnawa@fz-juelich.de>, Fabian Hoppe <f.hoppe@dlr.de>, Juan Pedro Gutiérrez Hermosillo Muriedas <juan.muriedas@kit.edu>, Hakan Akdag <hakan.akdag@dlr.de>, Berkant Palazoglu <b.palazoglu@fz-juelich.de>
License-Expression: MIT
Project-URL: Homepage, https://github.com/helmholtz-analytics/heat
Project-URL: Documentation, https://heat.readthedocs.io/
Project-URL: Repository, https://github.com/helmholtz-analytics/heat
Project-URL: Issues, https://github.com/helmholtz-analytics/heat/issues
Project-URL: Changelog, https://github.com/helmholtz-analytics/heat/blob/main/CHANGELOG.md
Keywords: data,analytics,tensors,distributed,gpu
Classifier: Development Status :: 5 - Production/Stable
Classifier: Programming Language :: Python :: 3.10
Classifier: Programming Language :: Python :: 3.11
Classifier: Programming Language :: Python :: 3.12
Classifier: Programming Language :: Python :: 3.13
Classifier: Intended Audience :: Science/Research
Classifier: Topic :: Scientific/Engineering
Classifier: Topic :: Scientific/Engineering :: Artificial Intelligence
Classifier: Topic :: Scientific/Engineering :: Information Analysis
Classifier: Topic :: Scientific/Engineering :: Mathematics
Classifier: Typing :: Typed
Requires-Python: >=3.10
License-File: LICENSE
Requires-Dist: mpi4py>=3.0.0
Requires-Dist: torch<2.10,~=2.0
Requires-Dist: torchvision~=0.15
Requires-Dist: scipy~=1.14
Provides-Extra: hdf5
Requires-Dist: h5py>=2.8.0; extra == "hdf5"
Provides-Extra: netcdf
Requires-Dist: netCDF4>=1.5.6; extra == "netcdf"
Provides-Extra: zarr
Requires-Dist: zarr; extra == "zarr"
Provides-Extra: examples
Requires-Dist: scikit-learn~=0.24; extra == "examples"
Requires-Dist: matplotlib~=3.1; extra == "examples"
Requires-Dist: jupyter; extra == "examples"
Requires-Dist: ipyparallel; extra == "examples"
Requires-Dist: pillow; extra == "examples"
Provides-Extra: dev
Requires-Dist: pre-commit; extra == "dev"
Requires-Dist: ruff; extra == "dev"
Requires-Dist: mypy; extra == "dev"
Requires-Dist: pytest; extra == "dev"
Requires-Dist: coverage; extra == "dev"
Requires-Dist: perun; extra == "dev"
Provides-Extra: docs
Requires-Dist: sphinx; extra == "docs"
Requires-Dist: sphinx_rtd_theme; extra == "docs"
Requires-Dist: sphinx-autoapi; extra == "docs"
Requires-Dist: nbsphinx; extra == "docs"
Requires-Dist: sphinx-autobuild; extra == "docs"
Requires-Dist: sphinx-copybutton; extra == "docs"
Dynamic: license-file
